LICENSE.txt
MANIFEST.in
README.rst
setup.py
spa_api.py
spa_phone_api.egg-info/PKG-INFO
spa_phone_api.egg-info/SOURCES.txt
spa_phone_api.egg-info/dependency_links.txt
spa_phone_api.egg-info/requires.txt
spa_phone_api.egg-info/top_level.txt