Metadata-Version: 1.1
Name: spa-phone-api
Version: 0.4.0
Summary: Provides an API for Cisco/Linksys/Sipura VoIP SPA Phones
Home-page: http://github.com/Bouke/spa-phone-api
Author: Bouke Haarsma
Author-email: bouke@webatoom.nl
License: MIT
Platform: UNKNOWN
Classifier: Development Status :: 4 - Beta
Classifier: Intended Audience :: Developers
Classifier: License :: OSI Approved :: MIT License
Classifier: Operating System :: OS Independent
Classifier: Programming Language :: Python
Classifier: Topic :: Communications :: Internet Phone
